latest/__init__.py
latest/__main__.py
latest/config.py
latest/core.py
latest/exceptions.py
latest/shortcuts.py
latest/util.py
latest-0.1.dist-info/DESCRIPTION.rst
latest-0.1.dist-info/METADATA
latest-0.1.dist-info/RECORD
latest-0.1.dist-info/WHEEL
latest-0.1.dist-info/entry_points.txt
latest-0.1.dist-info/metadata.json
latest-0.1.dist-info/top_level.txt
