Metadata-Version: 2.0
Name: latest
Version: 0.1
Summary: A LaTeX-oriented template engine.
Home-page: https://github.com/bluePhlavio/latest
Author: Flavio Grandin
Author-email: flavio.grandin@gmail.com
License: MIT
Keywords: latex template engine
Platform: UNKNOWN
Classifier: Development Status :: 3 - Alpha
Classifier: Intended Audience :: Developers
Classifier: Intended Audience :: Science/Research
Classifier: License :: OSI Approved :: MIT License
Classifier: Natural Language :: English
Classifier: Operating System :: OS Independent
Classifier: Programming Language :: Python :: 2
Classifier: Programming Language :: Python :: 2.6
Classifier: Programming Language :: Python :: 2.7
Classifier: Programming Language :: Python :: 3
Classifier: Programming Language :: Python :: 3.4
Classifier: Programming Language :: Python :: 3.5
Classifier: Programming Language :: Python :: 3.6
